geks/__init__.py
geks/edge.py
geks/geometry.py
geks/heightmap.py
geks/hexagon.py
geks/hexmap.py
geks/layout.py
geks/pathfinding.py
geks/rivers.py
geks/cython/__init__.py
geks/cython/fill_sinks.c
geks/cython/fill_sinks.cp310-win32.pyd
geks/front/__init__.py
geks/front/front_mpl.py
geks-0.0.1.dist-info/LICENSE
geks-0.0.1.dist-info/METADATA
geks-0.0.1.dist-info/WHEEL
geks-0.0.1.dist-info/top_level.txt
geks-0.0.1.dist-info/RECORD
