Metadata-Version: 2.1
Name: geks
Version: 0.0.1
Summary: Hexagonal mapmaking toolkit
Author-email: Vasily Negrebetskiy <kmiziz.com@gmail.com>
Project-URL: source, https://github.com/kompoth/geks
Classifier: Development Status :: 2 - Pre-Alpha
Classifier: Intended Audience :: Developers
Classifier: Topic :: Software Development :: Libraries :: Python Modules
Classifier: Topic :: Software Development
Classifier: Intended Audience :: Developers
Classifier: Operating System :: OS Independent
Classifier: Programming Language :: Python
Classifier: Programming Language :: Python :: 3 :: Only
Classifier: Programming Language :: Python :: 3.10
Classifier: Programming Language :: Python :: 3.11
Classifier: Programming Language :: Python :: 3.12
Classifier: Programming Language :: Cython
Classifier: License :: OSI Approved :: MIT License
Requires-Python: >=3.10
Provides-Extra: mpl
License-File: LICENSE
